sourcemerger/__init__.py
sourcemerger/__main__.py
sourcemerger/sourcemerger.py
sourcemerger-1.0.0.dist-info/METADATA
sourcemerger-1.0.0.dist-info/WHEEL
sourcemerger-1.0.0.dist-info/entry_points.txt
sourcemerger-1.0.0.dist-info/license.txt
sourcemerger-1.0.0.dist-info/top_level.txt
sourcemerger-1.0.0.dist-info/RECORD
