Metadata-Version: 2.1
Name: sourcemerger
Version: 1.0.0
Summary: sourcemerger is a command-line tool that generates a single-header C++ library from your source code.
Home-page: https://gitlab.com/russofrancesco/sourcemerger
Author: Francesco Russo
Author-email: sourcemerger@frusso.dev
License: MIT License
Keywords: sourcemerger,c++,single-header,library,concatenate,merge
Platform: UNKNOWN
Classifier: License :: OSI Approved :: MIT License
Classifier: Programming Language :: Python :: 3.6
Classifier: Programming Language :: Python :: 3.7
Classifier: Programming Language :: Python :: 3.8
Classifier: Programming Language :: C++
Classifier: Operating System :: OS Independent
Classifier: Intended Audience :: Developers
Classifier: Topic :: Utilities
Requires-Python: ~=3.6
